aurum/__init__.py
aurum/__main__.py
aurum/_about.py
aurum/client.py
aurum/commands/__init__.py
aurum/commands/app_command.py
aurum/commands/context_menu_command.py
aurum/commands/decorators/__init__.py
aurum/commands/decorators/sub_command.py
aurum/commands/enum/__init__.py
aurum/commands/enum/sync_commands.py
aurum/commands/message_command.py
aurum/commands/slash_command.py
aurum/commands/sub_command.py
aurum/commands/typing.py
aurum/commands/user_command.py
aurum/context.py
aurum/events.py
aurum/exceptions.py
aurum/ext/__init__.py
aurum/ext/plugins/__init__.py
aurum/ext/plugins/plugin.py
aurum/ext/plugins/plugin_manager.py
aurum/internal/__init__.py
aurum/internal/command_handler.py
aurum/internal/includable.py
aurum/internal/utils/__init__.py
aurum/internal/utils/commands.py
aurum/internal/version.py
aurum/l10n/__init__.py
aurum/l10n/localization_provider_interface.py
aurum/l10n/localized.py
aurum/l10n/types.py
aurum/options/__init__.py
aurum/options/choice.py
aurum/options/option.py
aurum/py.typed
aurum_hikari-0.1.5.7.dist-info/LICENSE
aurum_hikari-0.1.5.7.dist-info/METADATA
aurum_hikari-0.1.5.7.dist-info/WHEEL
aurum_hikari-0.1.5.7.dist-info/RECORD
