Metadata-Version: 2.1
Name: aurum-hikari
Version: 0.1.5.7
Summary: A flexible framework for handling commands and components.
License: MIT
Keywords: discord,hikari,commands,components,command-handler,component-handler,framework
Author: stefanlight8
Author-email: 64615032+stefanlight8@users.noreply.github.com
Requires-Python: >=3.10,<3.13
Classifier: Development Status :: 3 - Alpha
Classifier: Intended Audience :: Developers
Classifier: License :: OSI Approved :: MIT License
Classifier: Programming Language :: Python :: 3
Classifier: Programming Language :: Python :: 3.10
Classifier: Programming Language :: Python :: 3.11
Classifier: Programming Language :: Python :: 3.12
Classifier: Programming Language :: Python :: 3 :: Only
Classifier: Programming Language :: Python :: Implementation :: CPython
Classifier: Topic :: Communications :: Chat
Classifier: Topic :: Software Development :: Libraries
Classifier: Topic :: Software Development :: Libraries :: Python Modules
Classifier: Topic :: Utilities
Classifier: Typing :: Typed
Requires-Dist: attrs (>=23.2.0,<24.0.0)
Requires-Dist: hikari (>=2.0.0.dev122)
Project-URL: Issue Tracker, https://github.com/ShinshiDevs/aurum-hikari/issues
Project-URL: documentation, https://shinshidevs.github.io/aurum-hikari/
Project-URL: repository, https://github.com/ShinshiDevs/aurum-hikari
